nagato/__init__.py
nagato/service/__init__.py
nagato/service/embedding.py
nagato/service/finetune.py
nagato/service/prompts.py
nagato/service/vectordb.py
nagato/utils/__init__.py
nagato/utils/logger.py
nagato_ai-0.0.16.dist-info/LICENSE
nagato_ai-0.0.16.dist-info/METADATA
nagato_ai-0.0.16.dist-info/WHEEL
nagato_ai-0.0.16.dist-info/RECORD
