Metadata-Version: 2.1
Name: nagato-ai
Version: 0.0.16
Summary: 
Author: Ismail Pelaseyed
Requires-Python: >=3.9,<4.0
Classifier: Programming Language :: Python :: 3
Classifier: Programming Language :: Python :: 3.9
Classifier: Programming Language :: Python :: 3.10
Classifier: Programming Language :: Python :: 3.11
Requires-Dist: black (>=23.3.0,<24.0.0)
Requires-Dist: colorlog (>=6.7.0,<7.0.0)
Requires-Dist: flake8 (>=6.0.0,<7.0.0)
Requires-Dist: llama-index (>=0.8.37,<0.9.0)
Requires-Dist: pinecone-client (>=2.2.2,<3.0.0)
Requires-Dist: pydantic (>=1.10.7,<2.0.0)
Requires-Dist: pypdf (>=3.16.2,<4.0.0)
Requires-Dist: python-decouple (>=3.8,<4.0)
Requires-Dist: python-dotenv (>=1.0.0,<2.0.0)
Requires-Dist: replicate (>=0.15.4,<0.16.0)
Requires-Dist: requests (>=2.31.0,<3.0.0)
Requires-Dist: ruff (>=0.0.265,<0.0.266)
Requires-Dist: sentence-transformers (>=2.2.2,<3.0.0)
Requires-Dist: setuptools (>=68.2.2,<69.0.0)
Requires-Dist: tiktoken (>=0.5.1,<0.6.0)
Requires-Dist: tqdm (>=4.66.1,<5.0.0)
Requires-Dist: unstructured (>=0.10.16,<0.11.0)
Requires-Dist: vulture (>=2.7,<3.0)
Requires-Dist: wheel (>=0.41.0,<0.42.0)
